Workbook

Sheet Simulador Coste Boda
A1: SIMULADOR COSTE DE BODA
A2: Número de invitados (añadir) | B2: 100
A3: Vuestro presupuesto (añadir) | B3: 35000
A4: Coste estimado Boda | B4: =SUM(D9:D150) -> 32150
A5: Coste estimado por invitado | B5: 328
A6: Nombre del Gasto | B6: Coste estimado | E6: Contabilizar
A8: Columna1 | B8: Columna2 | C8: Columna3 | D8: Columna4 | E8: Columna5
A9: Lugar de Recepción/Celebración | B9: 8000 | C9: =IF(E9="Sí",1,0) -> 1 | D9: ='Simulador Coste Boda'!$B9*'Simulador Coste Boda'!$C9 -> 8000 | E9: Sí
A10: Alquiler del lugar de la ceremonia | B10: 3000 | C10: =IF(E10="Sí",1,0) -> 1 | D10: ='Simulador Coste Boda'!$B10*'Simulador Coste Boda'!$C10 -> 3000 | E10: Sí
A11: Catering | B11: 10000 | C11: =IF(E11="Sí",1,0) -> 1 | D11: ='Simulador Coste Boda'!$B11*'Simulador Coste Boda'!$C11 -> 10000 | E11: Sí
A12: Fotógrafo | B12: 1800 | C12: =IF(E12="Sí",1,0) -> 1 | D12: ='Simulador Coste Boda'!$B12*'Simulador Coste Boda'!$C12 -> 1800 | E12: Sí
A13: Vestido de novia | B13: 1800 | C13: =IF(E13="Sí",1,0) -> 1 | D13: ='Simulador Coste Boda'!$B13*'Simulador Coste Boda'!$C13 -> 1800 | E13: Sí
A14: Traje de novio | B14: 600 | C14: =IF(E14="Sí",1,0) -> 1 | D14: ='Simulador Coste Boda'!$B14*'Simulador Coste Boda'!$C14 -> 600 | E14: Sí
A15: Anillos de Boda | B15: 1400 | C15: =IF(E15="Sí",1,0) -> 1 | D15: ='Simulador Coste Boda'!$B15*'Simulador Coste Boda'!$C15 -> 1400 | E15: Sí
A16: Música | B16: 1500 | C16: =IF(E16="Sí",1,0) -> 1 | D16: ='Simulador Coste Boda'!$B16*'Simulador Coste Boda'!$C16 -> 1500 | E16: Sí
A17: Decoración | B17: 1200 | C17: =IF(E17="Sí",1,0) -> 1 | D17: ='Simulador Coste Boda'!$B17*'Simulador Coste Boda'!$C17 -> 1200 | E17: Sí
A18: Flores | B18: 1000 | C18: =IF(E18="Sí",1,0) -> 1 | D18: ='Simulador Coste Boda'!$B18*'Simulador Coste Boda'!$C18 -> 1000 | E18: Sí
A19: Papelería | B19: 300 | C19: =IF(E19="Sí",1,0) -> 1 | D19: ='Simulador Coste Boda'!$B19*'Simulador Coste Boda'!$C19 -> 300 | E19: Sí
A20: Tarta nupcial | B20: 500 | C20: =IF(E20="Sí",1,0) -> 1 | D20: ='Simulador Coste Boda'!$B20*'Simulador Coste Boda'!$C20 -> 500 | E20: Sí
... A143: Página web de la boda | B143: 0 | C143: =IF(E143="Sí",1,0) -> 0 | D143: ='Simulador Coste Boda'!$B143*'Simulador Coste Boda'!$C143 -> 0 | E143: No
C144: =IF(E144="Sí",1,0) -> 0 | D144: ='Simulador Coste Boda'!$B144*'Simulador Coste Boda'!$C144 -> 0 | E144: No
C145: =IF(E145="Sí",1,0) -> 0 | D145: ='Simulador Coste Boda'!$B145*'Simulador Coste Boda'!$C145 -> 0 | E145: No
C146: =IF(E146="Sí",1,0) -> 0 | D146: ='Simulador Coste Boda'!$B146*'Simulador Coste Boda'!$C146 -> 0 | E146: No
C147: =IF(E147="Sí",1,0) -> 0 | D147: ='Simulador Coste Boda'!$B147*'Simulador Coste Boda'!$C147 -> 0 | E147: No
C148: =IF(E148="Sí",1,0) -> 0 | D148: ='Simulador Coste Boda'!$B148*'Simulador Coste Boda'!$C148 -> 0 | E148: No
C149: =IF(E149="Sí",1,0) -> 0 | D149: ='Simulador Coste Boda'!$B149*'Simulador Coste Boda'!$C149 -> 0 | E149: No

Sheet Gastos
A1: GASTOS | H1: Nº de invitados previstos | I1: Coste Real por invitado
A2: COSTE REAL | B2: =D4 -> 23000 | C2: Coste estimado | D2: Coste Real | E2: Pagado | H2: 100 | I2: =D4/H2 -> 230
A3: ESTIMADO | B3: =C4 -> 41100
A4: Nombre del Gasto | C4: =SUM(C6:C63) -> 41100 | D4: =SUM(D6:D63) -> 23000 | E4: =SUM(E6:E63) -> 10600 | G4: Estado | H4: Proveedor | I4: Notas Proveedor
A5: Columna1 | B5: Columna2 | C5: Columna3 | D5: Columna4 | E5: Columna5 | F5: Columna6 | G5: Columna7 | H5: Columna8 | I5: Columna9
A6: Lugar de Recepción/Celebración | C6: 18000 | D6: 10000 | E6: 600 | F6: =D6-E6 -> 9400 | G6: =IF($D6="","",IF($F6=0,"Pagado",IF($E6>0,"Pago parcial","Pendiente"))) -> Pago parcial
A7: Alquiler del lugar de la ceremonia | C7: 3000 | D7: 3000 | F7: =D7-E7 -> 3000 | G7: =IF($D7="","",IF($F7=0,"Pagado",IF($E7>0,"Pago parcial","Pendiente"))) -> Pendiente
A8: Catering | C8: 10000 | D8: 10000 | E8: 10000 | F8: =D8-E8 -> 0 | G8: =IF($D8="","",IF($F8=0,"Pagado",IF($E8>0,"Pago parcial","Pendiente"))) -> Pagado
A9: Fotógrafo | C9: 1800 | F9: =D9-E9 -> 0 | G9: =IF($D9="","",IF($F9=0,"Pagado",IF($E9>0,"Pago parcial","Pendiente")))
A10: Vestido de novia | C10: 1800 | F10: =D10-E10 -> 0 | G10: =IF($D10="","",IF($F10=0,"Pagado",IF($E10>0,"Pago parcial","Pendiente")))
A11: Traje de novio | C11: 600 | F11: =D11-E11 -> 0 | G11: =IF($D11="","",IF($F11=0,"Pagado",IF($E11>0,"Pago parcial","Pendiente")))
A12: Anillos de Boda | C12: 1400 | F12: =D12-E12 -> 0 | G12: =IF($D12="","",IF($F12=0,"Pagado",IF($E12>0,"Pago parcial","Pendiente"))) | H12: Proveedor 1 | I12: Reservar con 3 meses de antelación
A13: Música | C13: 1500 | F13: =D13-E13 -> 0 | G13: =IF($D13="","",IF($F13=0,"Pagado",IF($E13>0,"Pago parcial","Pendiente"))) | H13: Proveedor 2
A14: Decoración | C14: 1200 | F14: =D14-E14 -> 0 | G14: =IF($D14="","",IF($F14=0,"Pagado",IF($E14>0,"Pago parcial","Pendiente")))
A15: Flores | C15: 1000 | F15: =D15-E15 -> 0 | G15: =IF($D15="","",IF($F15=0,"Pagado",IF($E15>0,"Pago parcial","Pendiente")))
A16: Papelería | C16: 300 | F16: =D16-E16 -> 0 | G16: =IF($D16="","",IF($F16=0,"Pagado",IF($E16>0,"Pago parcial","Pendiente")))
A17: Tarta nupcial | C17: 500 | F17: =D17-E17 -> 0 | G17: =IF($D17="","",IF($F17=0,"Pagado",IF($E17>0,"Pago parcial","Pendiente")))
A18: Peluquería | F18: =D18-E18 -> 0 | G18: =IF($D18="","",IF($F18=0,"Pagado",IF($E18>0,"Pago parcial","Pendiente")))
A19: Papelería | F19: =D19-E19 -> 0 | G19: =IF($D19="","",IF($F19=0,"Pagado",IF($E19>0,"Pago parcial","Pendiente")))
A20: Invitaciones Digitales | C20: 0 | F20: =D20-E20 -> 0 | G20: =IF($D20="","",IF($F20=0,"Pagado",IF($E20>0,"Pago parcial","Pendiente")))
F21: =D21-E21 -> 0 | G21: =IF($D21="","",IF($F21=0,"Pagado",IF($E21>0,"Pago parcial","Pendiente")))
F22: =D22-E22 -> 0 | G22: =IF($D22="","",IF($F22=0,"Pagado",IF($E22>0,"Pago parcial","Pendiente")))
F23: =D23-E23 -> 0 | G23: =IF($D23="","",IF($F23=0,"Pagado",IF($E23>0,"Pago parcial","Pendiente")))
F24: =D24-E24 -> 0 | G24: =IF($D24="","",IF($F24=0,"Pagado",IF($E24>0,"Pago parcial","Pendiente")))
F25: =D25-E25 -> 0 | G25: =IF($D25="","",IF($F25=0,"Pagado",IF($E25>0,"Pago parcial","Pendiente")))
F26: =D26-E26 -> 0 | G26: =IF($D26="","",IF($F26=0,"Pagado",IF($E26>0,"Pago parcial","Pendiente")))
F27: =D27-E27 -> 0 | G27: =IF($D27="","",IF($F27=0,"Pagado",IF($E27>0,"Pago parcial","Pendiente")))
F28: =D28-E28 -> 0 | G28: =IF($D28="","",IF($F28=0,"Pagado",IF($E28>0,"Pago parcial","Pendiente")))
F29: =D29-E29 -> 0 | G29: =IF($D29="","",IF($F29=0,"Pagado",IF($E29>0,"Pago parcial","Pendiente")))
F30: =D30-E30 -> 0 | G30: =IF($D30="","",IF($F30=0,"Pagado",IF($E30>0,"Pago parcial","Pendiente")))
F31: =D31-E31 -> 0 | G31: =IF($D31="","",IF($F31=0,"Pagado",IF($E31>0,"Pago parcial","Pendiente")))
F32: =D32-E32 -> 0 | G32: =IF($D32="","",IF($F32=0,"Pagado",IF($E32>0,"Pago parcial","Pendiente")))
... F63: =D63-E63 -> 0 | G63: =IF($D63="","",IF($F63=0,"Pagado",IF($E63>0,"Pago parcial","Pendiente")))

Sheet Resumen
A1: RESUMEN | C1: Notas
A2: Gasto Total | B2: =Gastos!B2 -> 23000 | C2: Toda la información se crea de manera automática a partir de los datos de las hojas
A3: Gasto por invitado | B3: =B2/(B4+B5) -> 3285.7143
A4: Nº de invitados | B4: =COUNTA(Invitados!C$4:C$197) -> 5
A5: Confirmados | B5: =COUNTIF(Invitados!C3:C197,"Sí") -> 2
A6: No confirmados | B6: =COUNTIF(Invitados!C3:C197,"No") -> 2
A7: No vienen | B7: =COUNTIF(Invitados!C3:C197,"No viene") -> 1
A8: Familia | B8: =COUNTIF(Invitados!D3:D197,"Familia") -> 3
A9: Amigos | B9: =COUNTIF(Invitados!D3:D197,"Amigos") -> 1
A10: Trabajo | B10: =COUNTIF(Invitados!D3:D197,"Trabajo") -> 1
A11: Estudios | B11: =COUNTIF(Invitados!D3:D197,"Estudios") -> 0
A12: Otros | B12: =COUNTIF(Invitados!D3:D197,"Otra") -> 0
A14: Celiacos | B14: =COUNTIF(Invitados!H3:H197,"Celiac@") -> 1
A15: Veganos | B15: =COUNTIF(Invitados!H3:H197,"Vegan@") -> 0
A16: Vegetarianos | B16: =COUNTIF(Invitados!H3:H197,"Vegetarian@") -> 1
A17: Intolerantes a la lactosa | B17: =COUNTIF(Invitados!H3:H197,"Intolerante a la lactosa") -> 0
A18: Intolerantes al huevo | B18: =COUNTIF(Invitados!H3:H197,"Intolerante al huevo") -> 0
A19: Intolerantes a los frutos secos | B19: =COUNTIF(Invitados!H3:H197,"Intolerante a los frutos secos") -> 0
A21: Necesitan Autobús de ida | B21: =COUNTIF(Invitados!I3:I197,"Sí") -> 1
A22: Necesitan Autobús de vuelta | B22: =COUNTIF(Invitados!I3:I197,"Sí") -> 1
A24: Mesa Nupcial | B24: =COUNTIF(Invitados!G3:G197,"Mesa Nupcial") -> 1
A25: Mesa 1 | B25: =COUNTIF(Invitados!G3:G198,"Mesa 1") -> 1
A26: Mesa 2 | B26: =COUNTIF(Invitados!G3:G198,"Mesa 2") -> 1
A27: Mesa 3 | B27: =COUNTIF(Invitados!G3:G198,"Mesa 3") -> 0
A28: Mesa 4 | B28: =COUNTIF(Invitados!G3:G198,"Mesa 4") -> 0

Sheet Invitados
A1: LISTA DE INVITADOS | B1: =COUNTA(Invitados!A$4:A$195) -> 5 | C1: =COUNTIF(C3:C195,"Sí") -> 2 | I1: =COUNTIF(I3:I195,"Sí") -> 1 | K1: =COUNTIF(K3:K195,"Sí") -> 1
C2: =COUNTIF(C3:C195,"No") -> 2
A3: Nombre invitad@ | B3: Teléfono/email | C3: Confirmado | D3: Relación | E3: Adulto/niño | F3: Invitación enviada | G3: Mesa | H3: Especificaciones Alimenticias | I3: Autobús Ida | J3: Hora/Turno i | K3: Autobús Vuelta | L3: Hora/Turno v | M3: Comentario
A4: Esta Fila está desbloqueada para probar | B4: 9156323215 | C4: Sí | D4: Familia | E4: Adulto | F4: Sí | G4: Mesa Nupcial | H4: Celiac@ | I4: Sí | K4: Sí | M4: Necesita asistencia Silla de Ruedas
A5: Pepe 1 | B5: 9156322025 | C5: No | D5: Familia | E5: Niño | G5: Mesa 1 | H5: Vegetarian@ | I5: No | K5: No
A6: Pepe 2 | B6: 5202356 | C6: No | D6: Familia | E6: Adulto | G6: Mesa 2 | I6: No
A7: Pepe 3 | B7: 36523054 | C7: No viene | D7: Trabajo | E7: Adulto | G7: Sin asignar
A8: Pepe 4 | B8: 6555896 | C8: Sí | D8: Amigos | E8: Adulto
G15: Sin asignar
G21: Sin asignar

Sheet Timeline
A1: TIMELINE
A2: Hora | B2: Evento | C2: Dirección | D2: Notas
A3: 0.5 | B3: Iglesia
A4: 0.54166667 | B4: Recepción de los invitados
A5: 0.58333333 | B5: Comida
